{"cameraMode":{"drawMode":0,"name":"Shaded","section":"Shading Mode"},"sceneLighting":true,"audioPlay":false,"sceneViewState":{"m_AlwaysRefresh":false,"showFog":true,"showSkybox":true,"showFlares":true,"showImageEffects":true,"showParticleSystems":true,"showVisualEffectGraphs":true,"m_FxEnabled":true},"in2DMode":false,"pivot":{"x":18.05303955078125,"y":0.1522364616394043,"z":22.999591827392579},"rotation":{"x":-0.2026635706424713,"y":-0.04639964550733566,"z":0.00961359590291977,"w":-0.9781026244163513},"size":10.0,"orthographic":false}